{
    "os": "Linux-5.4.0-150-generic-x86_64-with-glibc2.17",
    "python": "3.8.16",
    "heartbeatAt": "2024-03-18T04:28:18.136272",
    "startedAt": "2024-03-18T04:28:17.285414",
    "docker": null,
    "cuda": null,
    "args": [],
    "state": "running",
    "program": "/home/uqyluo/github/KECOR-active-3Ddet/tools/test.py",
    "codePath": "tools/test.py",
    "git": {
        "remote": "https://github.com/Luoyadan/KECOR-active-3Ddet.git",
        "commit": "6f409ad3002b90c4d72822313d7ab7e98721ac3d"
    },
    "email": "lyadanluol@gmail.com",
    "root": "/home/uqyluo/github/KECOR-active-3Ddet",
    "host": "gs618-8997",
    "username": "uqyluo",
    "executable": "/home/uqyluo/anaconda3/envs/active-3d/bin/python",
    "cpu_count": 12,
    "cpu_count_logical": 24,
    "cpu_freq": {
        "current": 2872.5572083333336,
        "min": 2200.0,
        "max": 4000.0
    },
    "cpu_freq_per_core": [
        {
            "current": 2395.016,
            "min": 2200.0,
            "max": 4000.0
        },
        {
            "current": 2395.347,
            "min": 2200.0,
            "max": 4000.0
        },
        {
            "current": 2395.428,
            "min": 2200.0,
            "max": 4000.0
        },
        {
            "current": 2862.214,
            "min": 2200.0,
            "max": 4000.0
        },
        {
            "current": 4187.663,
            "min": 2200.0,
            "max": 4000.0
        },
        {
            "current": 2377.427,
            "min": 2200.0,
            "max": 4000.0
        },
        {
            "current": 2388.192,
            "min": 2200.0,
            "max": 4000.0
        },
        {
            "current": 2415.464,
            "min": 2200.0,
            "max": 4000.0
        },
        {
            "current": 4186.953,
            "min": 2200.0,
            "max": 4000.0
        },
        {
            "current": 2389.25,
            "min": 2200.0,
            "max": 4000.0
        },
        {
            "current": 2394.504,
            "min": 2200.0,
            "max": 4000.0
        },
        {
            "current": 4183.66,
            "min": 2200.0,
            "max": 4000.0
        },
        {
            "current": 2389.498,
            "min": 2200.0,
            "max": 4000.0
        },
        {
            "current": 2394.63,
            "min": 2200.0,
            "max": 4000.0
        },
        {
            "current": 2394.124,
            "min": 2200.0,
            "max": 4000.0
        },
        {
            "current": 2511.872,
            "min": 2200.0,
            "max": 4000.0
        },
        {
            "current": 4186.783,
            "min": 2200.0,
            "max": 4000.0
        },
        {
            "current": 2394.961,
            "min": 2200.0,
            "max": 4000.0
        },
        {
            "current": 2393.792,
            "min": 2200.0,
            "max": 4000.0
        },
        {
            "current": 2593.257,
            "min": 2200.0,
            "max": 4000.0
        },
        {
            "current": 4184.81,
            "min": 2200.0,
            "max": 4000.0
        },
        {
            "current": 2387.46,
            "min": 2200.0,
            "max": 4000.0
        },
        {
            "current": 2357.434,
            "min": 2200.0,
            "max": 4000.0
        },
        {
            "current": 4181.634,
            "min": 2200.0,
            "max": 4000.0
        }
    ],
    "disk": {
        "total": 937.3305015563965,
        "used": 509.8446846008301
    },
    "gpu": "NVIDIA RTX A6000",
    "gpu_count": 2,
    "gpu_devices": [
        {
            "name": "NVIDIA RTX A6000",
            "memory_total": 51527024640
        },
        {
            "name": "NVIDIA RTX A6000",
            "memory_total": 51527024640
        }
    ],
    "memory": {
        "total": 251.6110954284668
    }
}
